llama_index/packs/multi_tenancy_rag/__init__.py
llama_index/packs/multi_tenancy_rag/base.py
llama_index_packs_multi_tenancy_rag-0.5.1.dist-info/METADATA
llama_index_packs_multi_tenancy_rag-0.5.1.dist-info/WHEEL
llama_index_packs_multi_tenancy_rag-0.5.1.dist-info/licenses/LICENSE
llama_index_packs_multi_tenancy_rag-0.5.1.dist-info/RECORD
