Metadata-Version: 2.4
Name: llama-index-packs-multi-tenancy-rag
Version: 0.5.1
Summary: llama-index packs multi_tenancy_rag integration
Author-email: Your Name <you@example.com>
Maintainer: ravi03071991
License-Expression: MIT
License-File: LICENSE
Keywords: multi,multi-tenancy,rag,tenancy
Requires-Python: <4.0,>=3.9
Requires-Dist: llama-index-core<0.15,>=0.13.0
Requires-Dist: llama-index-llms-openai<0.6,>=0.5.0
